{
  "animateLoading": true,
  "borderRadius": "{{appsmith.theme.borderRadius.appBorderRadius}}",
  "bottomRow": 46,
  "dynamicBindingPathList": [
    {
      "key": "truncateButtonColor"
    },
    {
      "key": "fontFamily"
    },
    {
      "key": "borderRadius"
    }
  ],
  "dynamicHeight": "AUTO_HEIGHT",
  "dynamicTriggerPathList": [],
  "fontFamily": "{{appsmith.theme.fontFamily.appFont}}",
  "fontSize": "1rem",
  "fontStyle": "BOLD",
  "isLoading": false,
  "isVisible": true,
  "key": "dflclze2b7",
  "leftColumn": 2,
  "maxDynamicHeight": 9000,
  "minDynamicHeight": 4,
  "minWidth": 450,
  "mobileBottomRow": 46,
  "mobileLeftColumn": 2,
  "mobileRightColumn": 18,
  "mobileTopRow": 42,
  "needsErrorInfo": false,
  "originalBottomRow": 46,
  "originalTopRow": 42,
  "overflow": "NONE",
  "parentColumnSpace": 15.166015625,
  "parentId": "53vpbq8yvp",
  "parentRowSpace": 10,
  "renderMode": "CANVAS",
  "responsiveBehavior": "fill",
  "rightColumn": 18,
  "shouldTruncate": false,
  "text": "ONG",
  "textAlign": "LEFT",
  "textColor": "#231F20",
  "topRow": 42,
  "truncateButtonColor": "{{appsmith.theme.colors.primaryColor}}",
  "type": "TEXT_WIDGET",
  "version": 1,
  "widgetId": "garnkybf0e",
  "widgetName": "Text1"
}